yapic.di-2.0.12.dist-info/RECORD
yapic.di-2.0.12.dist-info/LICENSE
yapic.di-2.0.12.dist-info/WHEEL
yapic.di-2.0.12.dist-info/top_level.txt
yapic.di-2.0.12.dist-info/METADATA
yapic/di/_di.pyi
yapic/di/__init__.py
yapic/di/inject.py
yapic/di/_di.cpython-38-darwin.so
