Metadata-Version: 2.1
Name: yapic.di
Version: 2.0.12
Summary: Very fast Dependency Injection library
Home-page: https://github.com/zozzz/yapic.di
Author: Zoltán Vetési
Author-email: vetesi.zoltan@gmail.com
License: BSD
Classifier: Development Status :: 4 - Beta
Classifier: License :: OSI Approved :: BSD License
Classifier: Operating System :: Microsoft :: Windows
Classifier: Operating System :: Unix
Classifier: Programming Language :: C++
Classifier: Programming Language :: Python :: 3.7
Classifier: Programming Language :: Python :: 3 :: Only
Classifier: Topic :: Software Development :: Libraries :: Python Modules
Classifier: Topic :: Utilities
Classifier: Typing :: Typed
Requires-Python: >=3.7
License-File: LICENSE
Provides-Extra: benchmark
Requires-Dist: pytest ; extra == 'benchmark'
Requires-Dist: pytest-benchmark ; extra == 'benchmark'
